merakiDataFetcher/__init__.py
merakiDataFetcher/meraki_data_fetcher.py
merakiDataFetcher/meraki_dataclasses/__init__.py
merakiDataFetcher/meraki_dataclasses/meraki_device.py
merakiDataFetcher/meraki_dataclasses/meraki_device_appliance.py
merakiDataFetcher/meraki_dataclasses/meraki_device_camera.py
merakiDataFetcher/meraki_dataclasses/meraki_device_sensor.py
merakiDataFetcher/meraki_dataclasses/meraki_device_switch.py
merakiDataFetcher/meraki_dataclasses/meraki_device_wireless.py
merakiDataFetcher/meraki_dataclasses/meraki_network.py
merakiDataFetcher/meraki_dataclasses/meraki_organization.py
merakiDataFetcher/meraki_dataclasses/meraki_port.py
merakiDataFetcher/meraki_dataclasses/meraki_port_appliance.py
merakiDataFetcher/meraki_dataclasses/meraki_port_switch.py
merakiDataFetcher/meraki_dataclasses/meraki_port_switch_profile.py
merakiDataFetcher-1.1.5.dist-info/LICENSE
merakiDataFetcher-1.1.5.dist-info/METADATA
merakiDataFetcher-1.1.5.dist-info/WHEEL
merakiDataFetcher-1.1.5.dist-info/top_level.txt
merakiDataFetcher-1.1.5.dist-info/RECORD
