Metadata-Version: 2.1
Name: merakiDataFetcher
Version: 1.1.5
Summary: Meraki Data Fetcher. Uses the Meraki SDK and Dataclasses to process data from Meraki.
Author: Timo Riedinger
Author-email: timo.riedinger@bechtle.com
License: MIT
Classifier: Programming Language :: Python :: 3.11
License-File: LICENSE
Requires-Dist: aiohttp ==3.8.6
Requires-Dist: aiosignal ==1.3.1
Requires-Dist: async-timeout ==4.0.3
Requires-Dist: attrs ==23.1.0
Requires-Dist: certifi ==2023.7.22
Requires-Dist: charset-normalizer ==3.3.0
Requires-Dist: docutils ==0.20.1
Requires-Dist: frozenlist ==1.4.0
Requires-Dist: idna ==3.4
Requires-Dist: importlib-metadata ==6.8.0
Requires-Dist: jaraco.classes ==3.3.0
Requires-Dist: keyring ==24.2.0
Requires-Dist: markdown-it-py ==3.0.0
Requires-Dist: mdurl ==0.1.2
Requires-Dist: meraki ==1.38.0
Requires-Dist: more-itertools ==10.1.0
Requires-Dist: multidict ==6.0.4
Requires-Dist: nh3 ==0.2.14
Requires-Dist: pkginfo ==1.9.6
Requires-Dist: Pygments ==2.16.1
Requires-Dist: readme-renderer ==42.0
Requires-Dist: requests ==2.31.0
Requires-Dist: requests-toolbelt ==1.0.0
Requires-Dist: rfc3986 ==2.0.0
Requires-Dist: rich ==13.6.0
Requires-Dist: twine ==4.0.2
Requires-Dist: urllib3 ==2.0.6
Requires-Dist: yarl ==1.9.2
Requires-Dist: zipp ==3.17.0
